{
  "$schema": "https://mintlify.com/docs.json",
  "name": "ChecadorCumbres",
  "theme": "linden",
  "colors": {
    "primary": "#040404",
    "light": "#ef370f",
    "dark": "#f79d72"
  },
  "favicon": "https://media.brand.dev/ef7cdb24-cf48-44b6-9439-4288899142b4.png",
  "logo": {
    "light": "https://media.brand.dev/69d705f4-5e9b-4d51-bd5f-4788b2d5c4d2.svg",
    "dark": "https://media.brand.dev/69d705f4-5e9b-4d51-bd5f-4788b2d5c4d2.svg"
  },
  "navbar": {
    "primary": {
      "type": "github",
      "href": "https://github.com/DevCISQPAQ/ChecadorCumbres"
    }
  },
  "footer": {
    "socials": {
      "github": "https://github.com/DevCISQPAQ/ChecadorCumbres"
    }
  },
  "navigation": {
    "tabs": [
      {
        "tab": "Documentation",
        "groups": [
          {
            "group": "Getting Started",
            "pages": ["introduction", "installation", "quickstart"]
          },
          {
            "group": "Core Features",
            "pages": [
              "features/employee-management",
              "features/attendance-tracking",
              "features/schedule-types",
              "features/reporting"
            ]
          },
          {
            "group": "User Guides",
            "pages": [
              "guides/admin-dashboard",
              "guides/check-in-out",
              "guides/managing-employees",
              "guides/generating-reports"
            ]
          },
          {
            "group": "Configuration",
            "pages": [
              "configuration/environment",
              "configuration/database",
              "configuration/system-settings",
              "configuration/email-notifications"
            ]
          }
        ]
      },
      {
        "tab": "API Reference",
        "groups": [
          {
            "group": "Overview",
            "pages": ["api/introduction", "api/authentication"]
          },
          {
            "group": "Endpoints",
            "pages": [
              "api/endpoints/employees",
              "api/endpoints/attendance",
              "api/endpoints/reports",
              "api/endpoints/users"
            ]
          },
          {
            "group": "Models",
            "pages": [
              "api/models/employee",
              "api/models/asistencia",
              "api/models/user",
              "api/models/configuracion"
            ]
          }
        ]
      }
    ]
  }
}
